CHANGELOG.txt
HISTORY.md
LICENSE.txt
MANIFEST.in
README.md
README.txt
setup.py
payUnit/__init__.py
payUnit.egg-info/PKG-INFO
payUnit.egg-info/SOURCES.txt
payUnit.egg-info/dependency_links.txt
payUnit.egg-info/requires.txt
payUnit.egg-info/top_level.txt