Metadata-Version: 2.1
Name: payUnit
Version: 0.2.2
Summary: Python sdk for payUnit payments, including Mtn momo,Orange momo,Express Union
Home-page: UNKNOWN
Author: SevenGps
Author-email: info@sevengps.com
License: MIT
Keywords: payUnit,momo,payment
Platform: UNKNOWN
Classifier: Development Status :: 5 - Production/Stable
Classifier: Intended Audience :: Developers
Classifier: Operating System :: Microsoft :: Windows :: Windows 10
Classifier: License :: OSI Approved :: MIT License
Classifier: Programming Language :: Python :: 3
